edx_ace/__init__.py
edx_ace/ace.py
edx_ace/apps.py
edx_ace/delivery.py
edx_ace/errors.py
edx_ace/message.py
edx_ace/monitoring.py
edx_ace/policy.py
edx_ace/presentation.py
edx_ace/recipient.py
edx_ace/recipient_resolver.py
edx_ace/renderers.py
edx_ace/serialization.py
edx_ace/signals.py
edx_ace/channel/__init__.py
edx_ace/channel/braze.py
edx_ace/channel/django_email.py
edx_ace/channel/file.py
edx_ace/channel/mixins.py
edx_ace/channel/push_notification.py
edx_ace/channel/sailthru.py
edx_ace/push_notifications/views/__init__.py
edx_ace/templatetags/acetags.py
edx_ace/test_utils/__init__.py
edx_ace/tests/test_ace.py
edx_ace/tests/test_date.py
edx_ace/tests/test_delivery.py
edx_ace/tests/test_message.py
edx_ace/tests/test_policy.py
edx_ace/tests/test_presentation.py
edx_ace/tests/channel/test_braze.py
edx_ace/tests/channel/test_channel_helpers.py
edx_ace/tests/channel/test_django_email.py
edx_ace/tests/channel/test_file_email.py
edx_ace/tests/channel/test_push_notification.py
edx_ace/tests/channel/test_sailthru.py
edx_ace/tests/test_templates/testapp/edx_ace/testmessage/email/body.html
edx_ace/tests/test_templates/testapp/edx_ace/testmessage/email/head.html
edx_ace/tests/utils/test_signals.py
edx_ace/utils/__init__.py
edx_ace/utils/date.py
edx_ace/utils/once.py
edx_ace/utils/plugins.py
edx_ace/utils/signals.py
edx_ace-1.15.0.dist-info/licenses/LICENSE.txt
edx_ace-1.15.0.dist-info/METADATA
edx_ace-1.15.0.dist-info/WHEEL
edx_ace-1.15.0.dist-info/entry_points.txt
edx_ace-1.15.0.dist-info/top_level.txt
edx_ace-1.15.0.dist-info/RECORD
