Metadata-Version: 2.4
Name: edx-ace
Version: 1.15.0
Summary: Framework for Messaging
Home-page: https://github.com/openedx/edx-ace
Author: edX
Author-email: oscm@edx.org
License: AGPL 3.0
Keywords: Django edx
Classifier: Development Status :: 3 - Alpha
Classifier: Framework :: Django
Classifier: Framework :: Django :: 4.2
Classifier: Framework :: Django :: 5.2
Classifier: Intended Audience :: Developers
Classifier: License :: OSI Approved :: GNU Affero General Public License v3 or later (AGPLv3+)
Classifier: Natural Language :: English
Classifier: Programming Language :: Python :: 3
Classifier: Programming Language :: Python :: 3.12
License-File: LICENSE.txt
Requires-Dist: Django>=2.2
Requires-Dist: attrs>=17.2.0
Requires-Dist: django-push-notifications
Requires-Dist: edx-django-utils>=5.14.2
Requires-Dist: firebase-admin
Requires-Dist: python-dateutil
Requires-Dist: sailthru-client==2.2.3
Requires-Dist: six
Requires-Dist: stevedore>=1.10.0
Provides-Extra: sailthru
Requires-Dist: sailthru-client<2.3,>2.2; extra == "sailthru"
Provides-Extra: push-notifications
Requires-Dist: django-push-notifications[FCM]; extra == "push-notifications"
Dynamic: author
Dynamic: author-email
Dynamic: classifier
Dynamic: description
Dynamic: description-content-type
Dynamic: home-page
Dynamic: keywords
Dynamic: license
Dynamic: license-file
Dynamic: provides-extra
Dynamic: requires-dist
Dynamic: summary
